LICENSE
README.md
pyproject.toml
setup.py
src/embit/__init__.py
src/embit/base.py
src/embit/base58.py
src/embit/bech32.py
src/embit/bip32.py
src/embit/bip39.py
src/embit/bip85.py
src/embit/compact.py
src/embit/ec.py
src/embit/finalizer.py
src/embit/hashes.py
src/embit/misc.py
src/embit/networks.py
src/embit/psbt.py
src/embit/psbtview.py
src/embit/script.py
src/embit/slip39.py
src/embit/transaction.py
src/embit.egg-info/PKG-INFO
src/embit.egg-info/SOURCES.txt
src/embit.egg-info/dependency_links.txt
src/embit.egg-info/requires.txt
src/embit.egg-info/top_level.txt
src/embit/descriptor/__init__.py
src/embit/descriptor/arguments.py
src/embit/descriptor/base.py
src/embit/descriptor/checksum.py
src/embit/descriptor/descriptor.py
src/embit/descriptor/errors.py
src/embit/descriptor/miniscript.py
src/embit/descriptor/taptree.py
src/embit/liquid/__init__.py
src/embit/liquid/addresses.py
src/embit/liquid/blech32.py
src/embit/liquid/blip32.py
src/embit/liquid/descriptor.py
src/embit/liquid/finalizer.py
src/embit/liquid/networks.py
src/embit/liquid/pset.py
src/embit/liquid/psetview.py
src/embit/liquid/slip77.py
src/embit/liquid/transaction.py
src/embit/util/__init__.py
src/embit/util/ctypes_secp256k1.py
src/embit/util/key.py
src/embit/util/py_ripemd160.py
src/embit/util/py_secp256k1.py
src/embit/util/secp256k1.py
src/embit/util/prebuilt/libsecp256k1_darwin_arm64.dylib
src/embit/util/prebuilt/libsecp256k1_darwin_x86_64.dylib
src/embit/util/prebuilt/libsecp256k1_linux_aarch64.so
src/embit/util/prebuilt/libsecp256k1_linux_armv6l.so
src/embit/util/prebuilt/libsecp256k1_linux_armv7l.so
src/embit/util/prebuilt/libsecp256k1_linux_x86_64.so
src/embit/util/prebuilt/libsecp256k1_windows_amd64.dll
src/embit/wordlists/__init__.py
src/embit/wordlists/base.py
src/embit/wordlists/bip39.py
src/embit/wordlists/slip39.py
src/embit/wordlists/ubip39.py
src/embit/wordlists/uslip39.py