Metadata-Version: 2.1
Name: embit
Version: 0.8.0
Summary: A minimal bitcoin library for MicroPython and Python3 with a focus on embedded systems.
Author-email: Stepan Snigirev <snigirev.stepan@gmail.com>
Classifier: Programming Language :: Python :: 3
Classifier: License :: OSI Approved :: MIT License
Classifier: Operating System :: OS Independent
Provides-Extra: dev
License-File: LICENSE
